{
  "name": "@bizcharts/other-kernel-smooth-regression-2",
  "title": "Bizcharts基础图表",
  "description": "Bizhcarts basic charts",
  "source": {
    "type": "npm",
    "npm": "@bizcharts/other-kernel-smooth-regression-2",
    "version": "0.0.7",
    "sourceCodeDirectory": "src/"
  },
  "categories": [
    "图表",
    "可视化",
    "bizcharts",
    "基础图表",
    "other",
    "其他图表"
  ],
  "screenshot": "https://img.alicdn.com/tfs/TB1gvAmxgmTBuNjy1XbXXaMrVXa-1608-1248.png",
  "features": {
    "participle": {}
  },
  "publishTime": "2018-06-12T15:08:08.325Z",
  "updateTime": "2018-06-19T04:00:46.546Z",
  "participle": [
    "bizcharts"
  ],
  "components": {
    "@antv/data-set": "^0.8.9",
    "bizcharts": "^3.1.7"
  },
  "type": "react",
  "author": "昔夜"
}
